HA.v
module HA(x,y,sum,cout);

input x,y;
output sum,cout;

xor xor1(sum,x,y);
and and1(cout,x,y);
endmodule

FA.v
module FA (input A,B,Cin,output S,Cout);

wire has,hac,ha2c;

HA ha1(A,B,has,hac);
HA ha2(Cin,has,S,ha2c);
or or1(Cout,hac,ha2c);

endmodule

FourBitRCA.v
`timescale 1ns / 1ps
//////////////////////////////////////////////////////////////////////////////////
// Company: 
// Engineer: 
// 
// Create Date:    17:21:25 02/10/2016 
// Design Name: 
// Module Name:    FourBitRCA 
// Project Name: 
// Target Devices: 
// Tool versions: 
// Description: 
//
// Dependencies: 
//
// Revision: 
// Revision 0.01 - File Created
// Additional Comments: 
//
//////////////////////////////////////////////////////////////////////////////////
module FourBitRCA(
    input [3:0] a,
    input [3:0] b,
    input cin,
    output [3:0] sum,
    output cout
    );

wire c_out[2:0];
wire b_c[3:0];

xor (b_c[0],b[0],cin);
xor (b_c[1],b[1],cin);
xor (b_c[2],b[2],cin);
xor (b_c[3],b[3],cin);

FA fa1(a[0],b_c[0],cin,sum[0],c_out[0]);
FA fa2(a[1],b_c[1],c_out[0],sum[1],c_out[1]);
FA fa3(a[2],b_c[2],c_out[1],sum[2],c_out[2]);
FA fa4(a[3],b_c[3],c_out[2],sum[3],cout);

endmodule

FourBitRCA_tb.v
`timescale 1ns / 1ps

////////////////////////////////////////////////////////////////////////////////
// Company: 
// Engineer:
//
// Create Date:   17:39:52 02/10/2016
// Design Name:   FourBitRCA
// Module Name:   C:/Users/cmg128/Desktop/projects/FourBitRCA/FourBitRCA_tb.v
// Project Name:  FourBitRCA
// Target Device:  
// Tool versions:  
// Description: 
//
// Verilog Test Fixture created by ISE for module: FourBitRCA
//
// Dependencies:
// 
// Revision:
// Revision 0.01 - File Created
// Additional Comments:
// 
////////////////////////////////////////////////////////////////////////////////

module FourBitRCA_tb;

	// Inputs
	reg [3:0] a;
	reg [3:0] b;
	reg cin;
	reg [1:0] i;
	reg [4:0]j,k;
	
	// Outputs
	wire [3:0] sum;
	wire cout;

	integer outfile;

	// Instantiate the Unit Under Test (UUT)
	FourBitRCA RCA(
		.a(a), 
		.b(b), 
		.cin(cin), 
		.sum(sum), 
		.cout(cout)
	);

	initial begin
		// Initialize Inputs
		a = 0;
		b = 0;
		cin = 0;
		#10
      for(i=0; i<2; i=i+1) begin
			for(j=0;j<16;j=j+1)begin
				for(k=0;k<16;k=k+1)begin
					cin = i;
					a = j;
					b = k;
					#50;
					$fdisplay(outfile,"%b,%b,%b,%b%b",a,b,cin,cout,sum);
				end
			end
		end
	$fclose(outfile);
	$finish;
	end

	initial begin
	$dumpfile("FourBitRCA_output.vcd");
	$dumpvars(0,RCA);
	end

initial begin
	outfile = $fopen("./RCA_output.csv","w");
	$fdisplay(outfile,"A,B,Cin,CSum");
end
      
endmodule

FourBit_output.vcd
$date
	Thu Feb 11 22:25:59 2016
$end
$version
	Icarus Verilog
$end
$timescale
	1ps
$end
$scope module FourBitRCA_tb $end
$scope module RCA $end
$var wire 4 ! a [3:0] $end
$var wire 4 " b [3:0] $end
$var wire 1 # cin $end
$var wire 1 $ cout $end
$var wire 4 % sum [3:0] $end
$scope module fa1 $end
$var wire 1 & A $end
$var wire 1 ' B $end
$var wire 1 # Cin $end
$var wire 1 ( Cout $end
$var wire 1 ) S $end
$var wire 1 * ha2c $end
$var wire 1 + hac $end
$var wire 1 , has $end
$scope module ha1 $end
$var wire 1 + cout $end
$var wire 1 , sum $end
$var wire 1 & x $end
$var wire 1 ' y $end
$upscope $end
$scope module ha2 $end
$var wire 1 * cout $end
$var wire 1 ) sum $end
$var wire 1 # x $end
$var wire 1 , y $end
$upscope $end
$upscope $end
$scope module fa2 $end
$var wire 1 - A $end
$var wire 1 . B $end
$var wire 1 ( Cin $end
$var wire 1 / Cout $end
$var wire 1 0 S $end
$var wire 1 1 ha2c $end
$var wire 1 2 hac $end
$var wire 1 3 has $end
$scope module ha1 $end
$var wire 1 2 cout $end
$var wire 1 3 sum $end
$var wire 1 - x $end
$var wire 1 . y $end
$upscope $end
$scope module ha2 $end
$var wire 1 1 cout $end
$var wire 1 0 sum $end
$var wire 1 ( x $end
$var wire 1 3 y $end
$upscope $end
$upscope $end
$scope module fa3 $end
$var wire 1 4 A $end
$var wire 1 5 B $end
$var wire 1 / Cin $end
$var wire 1 6 Cout $end
$var wire 1 7 S $end
$var wire 1 8 ha2c $end
$var wire 1 9 hac $end
$var wire 1 : has $end
$scope module ha1 $end
$var wire 1 9 cout $end
$var wire 1 : sum $end
$var wire 1 4 x $end
$var wire 1 5 y $end
$upscope $end
$scope module ha2 $end
$var wire 1 8 cout $end
$var wire 1 7 sum $end
$var wire 1 / x $end
$var wire 1 : y $end
$upscope $end
$upscope $end
$scope module fa4 $end
$var wire 1 ; A $end
$var wire 1 < B $end
$var wire 1 6 Cin $end
$var wire 1 $ Cout $end
$var wire 1 = S $end
$var wire 1 > ha2c $end
$var wire 1 ? hac $end
$var wire 1 @ has $end
$scope module ha1 $end
$var wire 1 ? cout $end
$var wire 1 @ sum $end
$var wire 1 ; x $end
$var wire 1 < y $end
$upscope $end
$scope module ha2 $end
$var wire 1 > cout $end
$var wire 1 = sum $end
$var wire 1 6 x $end
$var wire 1 @ y $end
$upscope $end
$upscope $end
$upscope $end
$upscope $end
$enddefinitions $end
#0
$dumpvars
0@
0?
0>
0=
0<
0;
0:
09
08
07
06
05
04
03
02
01
00
0/
0.
0-
0,
0+
0*
0)
0(
0'
0&
b0 %
0$
0#
b0 "
b0 !
$end
#60000
1)
b1 %
1,
1'
b1 "
#110000
0)
10
b10 %
0,
13
0'
1.
b10 "
#160000
1)
b11 %
1,
1'
b11 "
#210000
0)
00
17
b100 %
0,
03
1:
0'
0.
15
b100 "
#260000
1)
b101 %
1,
1'
b101 "
#310000
0)
10
b110 %
0,
13
0'
1.
b110 "
#360000
1)
b111 %
1,
1'
b111 "
#410000
0)
00
07
1=
b1000 %
0,
03
0:
1@
0'
0.
05
1<
b1000 "
#460000
1)
b1001 %
1,
1'
b1001 "
#510000
0)
10
b1010 %
0,
13
0'
1.
b1010 "
#560000
1)
b1011 %
1,
1'
b1011 "
#610000
0)
00
17
b1100 %
0,
03
1:
0'
0.
15
b1100 "
#660000
1)
b1101 %
1,
1'
b1101 "
#710000
0)
10
b1110 %
0,
13
0'
1.
b1110 "
#760000
1)
b1111 %
1,
1'
b1111 "
#810000
00
07
0=
03
0:
0@
1)
b1 %
0(
0'
0.
05
0<
1,
0+
1&
b0 "
b1 !
#860000
10
0)
b10 %
1(
0,
1+
1'
b1 "
#910000
07
0/
1)
0(
10
b11 %
01
1,
0+
13
0'
1.
b10 "
#960000
17
1/
00
11
0)
b100 %
1(
0,
1+
1'
b11 "
#1010000
0=
0/
06
1)
0(
00
01
17
b101 %
08
1,
0+
03
1:
0'
0.
15
b100 "
#1060000
10
0)
b110 %
1(
0,
1+
1'
b101 "
#1110000
0=
06
17
08
0/
1)
0(
10
b111 %
01
1,
0+
13
0'
1.
b110 "
#1160000
1=
16
07
18
1/
00
11
0)
b1000 %
1(
0,
1+
1'
b111 "
#1210000
0/
06
0$
1)
0(
00
01
07
08
1=
b1001 %
0>
1,
0+
03
0:
1@
0'
0.
05
1<
b1000 "
#1260000
10
0)
b1010 %
1(
0,
1+
1'
b1001 "
#1310000
07
0/
1)
0(
10
b1011 %
01
1,
0+
13
0'
1.
b1010 "
#1360000
17
1/
00
11
0)
b1100 %
1(
0,
1+
1'
b1011 "
#1410000
0$
1=
0>
0/
06
1)
0(
00
01
17
b1101 %
08
1,
0+
03
1:
0'
0.
15
b1100 "
#1460000
10
0)
b1110 %
1(
0,
1+
1'
b1101 "
#1510000
0$
1=
0>
06
17
08
0/
1)
0(
10
b1111 %
01
1,
0+
13
0'
1.
b1110 "
#1560000
1$
0=
1>
16
07
18
1/
00
11
0)
b0 %
1(
0,
1+
1'
b1111 "
#1610000
06
0$
08
0=
0>
0/
0:
0@
0)
0(
10
b10 %
01
0'
0.
05
0<
0,
0+
13
02
0&
1-
b0 "
b10 !
#1660000
1)
b11 %
1,
1'
b1 "
#1710000
17
0)
00
b100 %
1/
0,
03
12
0'
1.
b10 "
#1760000
1)
b101 %
1,
1'
b11 "
#1810000
0=
06
0)
10
0/
17
b110 %
08
0,
13
02
1:
0'
0.
15
b100 "
#1860000
1)
b111 %
1,
1'
b101 "
#1910000
1=
16
07
18
0)
00
b1000 %
1/
0,
03
12
0'
1.
b110 "
#1960000
1)
b1001 %
1,
1'
b111 "
#2010000
06
0$
0)
10
0/
07
08
1=
b1010 %
0>
0,
13
02
0:
1@
0'
0.
05
1<
b1000 "
#2060000
1)
b1011 %
1,
1'
b1001 "
#2110000
17
0)
00
b1100 %
1/
0,
03
12
0'
1.
b1010 "
#2160000
1)
b1101 %
1,
1'
b1011 "
#2210000
0$
1=
0>
06
0)
10
0/
17
b1110 %
08
0,
13
02
1:
0'
0.
15
b1100 "
#2260000
1)
b1111 %
1,
1'
b1101 "
#2310000
1$
0=
1>
16
07
18
0)
00
b0 %
1/
0,
03
12
0'
1.
b1110 "
#2360000
1)
b1 %
1,
1'
b1111 "
#2410000
0/
10
06
0$
07
08
0=
0>
01
13
02
0:
0@
1)
b11 %
0(
0'
0.
05
0<
1,
0+
1&
b0 "
b11 !
#2460000
17
1/
00
11
0)
b100 %
1(
0,
1+
1'
b1 "
#2510000
1)
0(
00
b101 %
01
1,
0+
03
12
0'
1.
b10 "
#2560000
10
0)
b110 %
1(
0,
1+
1'
b11 "
#2610000
0=
06
1)
0(
10
01
0/
17
b111 %
08
1,
0+
13
02
1:
0'
0.
15
b100 "
#2660000
1=
16
07
18
1/
00
11
0)
b1000 %
1(
0,
1+
1'
b101 "
#2710000
1)
0(
00
b1001 %
01
1,
0+
03
12
0'
1.
b110 "
#2760000
10
0)
b1010 %
1(
0,
1+
1'
b111 "
#2810000
06
0$
1)
0(
10
01
0/
07
08
1=
b1011 %
0>
1,
0+
13
02
0:
1@
0'
0.
05
1<
b1000 "
#2860000
17
1/
00
11
0)
b1100 %
1(
0,
1+
1'
b1001 "
#2910000
1)
0(
00
b1101 %
01
1,
0+
03
12
0'
1.
b1010 "
#2960000
10
0)
b1110 %
1(
0,
1+
1'
b1011 "
#3010000
0$
1=
0>
06
1)
0(
10
01
0/
17
b1111 %
08
1,
0+
13
02
1:
0'
0.
15
b1100 "
#3060000
1$
0=
1>
16
07
18
1/
00
11
0)
b0 %
1(
0,
1+
1'
b1101 "
#3110000
1)
0(
00
b1 %
01
1,
0+
03
12
0'
1.
b1110 "
#3160000
10
0)
b10 %
1(
0,
1+
1'
b1111 "
#3210000
0=
0$
0>
06
0@
0)
0(
00
01
0/
17
b100 %
08
0'
0.
05
0<
0,
0+
03
02
1:
09
0&
0-
14
b0 "
b100 !
#3260000
1)
b101 %
1,
1'
b1 "
#3310000
0)
10
b110 %
0,
13
0'
1.
b10 "
#3360000
1)
b111 %
1,
1'
b11 "
#3410000
1=
0)
00
07
b1000 %
16
0,
03
0:
19
0'
0.
15
b100 "
#3460000
1)
b1001 %
1,
1'
b101 "
#3510000
0)
10
b1010 %
0,
13
0'
1.
b110 "
#3560000
1)
b1011 %
1,
1'
b111 "
#3610000
0$
0)
00
17
06
1=
b1100 %
0>
0,
03
1:
09
1@
0'
0.
05
1<
b1000 "
#3660000
1)
b1101 %
1,
1'
b1001 "
#3710000
0)
10
b1110 %
0,
13
0'
1.
b1010 "
#3760000
1)
b1111 %
1,
1'
b1011 "
#3810000
1$
0=
1>
0)
00
07
b0 %
16
0,
03
0:
19
0'
0.
15
b1100 "
#3860000
1)
b1 %
1,
1'
b1101 "
#3910000
0)
10
b10 %
0,
13
0'
1.
b1110 "
#3960000
1)
b11 %
1,
1'
b1111 "
#4010000
00
0$
17
06
0=
0>
03
1:
09
0@
1)
b101 %
0(
0'
0.
05
0<
1,
0+
1&
b0 "
b101 !
#4060000
10
0)
b110 %
1(
0,
1+
1'
b1 "
#4110000
0=
06
17
08
0/
1)
0(
10
b111 %
01
1,
0+
13
0'
1.
b10 "
#4160000
1=
16
07
18
1/
00
11
0)
b1000 %
1(
0,
1+
1'
b11 "
#4210000
0/
1)
0(
00
01
07
b1001 %
08
1,
0+
03
0:
19
0'
0.
15
b100 "
#4260000
10
0)
b1010 %
1(
0,
1+
1'
b101 "
#4310000
07
0/
1)
0(
10
b1011 %
01
1,
0+
13
0'
1.
b110 "
#4360000
17
1/
00
11
0)
b1100 %
1(
0,
1+
1'
b111 "
#4410000
0/
0$
1)
0(
00
01
17
08
06
1=
b1101 %
0>
1,
0+
03
1:
09
1@
0'
0.
05
1<
b1000 "
#4460000
10
0)
b1110 %
1(
0,
1+
1'
b1001 "
#4510000
0$
1=
0>
06
17
08
0/
1)
0(
10
b1111 %
01
1,
0+
13
0'
1.
b1010 "
#4560000
1$
0=
1>
16
07
18
1/
00
11
0)
b0 %
1(
0,
1+
1'
b1011 "
#4610000
0/
1)
0(
00
01
07
b1 %
08
1,
0+
03
0:
19
0'
0.
15
b1100 "
#4660000
10
0)
b10 %
1(
0,
1+
1'
b1101 "
#4710000
07
0/
1)
0(
10
b11 %
01
1,
0+
13
0'
1.
b1110 "
#4760000
17
1/
00
11
0)
b100 %
1(
0,
1+
1'
b1111 "
#4810000
0$
06
0=
0>
0/
1:
09
0@
0)
0(
10
b110 %
01
0'
0.
05
0<
0,
0+
13
02
0&
1-
b0 "
b110 !
#4860000
1)
b111 %
1,
1'
b1 "
#4910000
1=
16
07
18
0)
00
b1000 %
1/
0,
03
12
0'
1.
b10 "
#4960000
1)
b1001 %
1,
1'
b11 "
#5010000
0)
10
0/
07
b1010 %
08
0,
13
02
0:
19
0'
0.
15
b100 "
#5060000
1)
b1011 %
1,
1'
b101 "
#5110000
17
0)
00
b1100 %
1/
0,
03
12
0'
1.
b110 "
#5160000
1)
b1101 %
1,
1'
b111 "
#5210000
0$
0)
10
0/
17
08
06
1=
b1110 %
0>
0,
13
02
1:
09
1@
0'
0.
05
1<
b1000 "
#5260000
1)
b1111 %
1,
1'
b1001 "
#5310000
1$
0=
1>
16
07
18
0)
00
b0 %
1/
0,
03
12
0'
1.
b1010 "
#5360000
1)
b1 %
1,
1'
b1011 "
#5410000
0)
10
0/
07
b10 %
08
0,
13
02
0:
19
0'
0.
15
b1100 "
#5460000
1)
b11 %
1,
1'
b1101 "
#5510000
17
0)
00
b100 %
1/
0,
03
12
0'
1.
b1110 "
#5560000
1)
b101 %
1,
1'
b1111 "
#5610000
0/
10
0$
17
08
06
0=
0>
01
13
02
1:
09
0@
1)
b111 %
0(
0'
0.
05
0<
1,
0+
1&
b0 "
b111 !
#5660000
1=
16
07
18
1/
00
11
0)
b1000 %
1(
0,
1+
1'
b1 "
#5710000
1)
0(
00
b1001 %
01
1,
0+
03
12
0'
1.
b10 "
#5760000
10
0)
b1010 %
1(
0,
1+
1'
b11 "
#5810000
1)
0(
10
01
0/
07
b1011 %
08
1,
0+
13
02
0:
19
0'
0.
15
b100 "
#5860000
17
1/
00
11
0)
b1100 %
1(
0,
1+
1'
b101 "
#5910000
1)
0(
00
b1101 %
01
1,
0+
03
12
0'
1.
b110 "
#5960000
10
0)
b1110 %
1(
0,
1+
1'
b111 "
#6010000
0$
1)
0(
10
01
0/
17
08
06
1=
b1111 %
0>
1,
0+
13
02
1:
09
1@
0'
0.
05
1<
b1000 "
#6060000
1$
0=
1>
16
07
18
1/
00
11
0)
b0 %
1(
0,
1+
1'
b1001 "
#6110000
1)
0(
00
b1 %
01
1,
0+
03
12
0'
1.
b1010 "
#6160000
10
0)
b10 %
1(
0,
1+
1'
b1011 "
#6210000
1)
0(
10
01
0/
07
b11 %
08
1,
0+
13
02
0:
19
0'
0.
15
b1100 "
#6260000
17
1/
00
11
0)
b100 %
1(
0,
1+
1'
b1101 "
#6310000
1)
0(
00
b101 %
01
1,
0+
03
12
0'
1.
b1110 "
#6360000
10
0)
b110 %
1(
0,
1+
1'
b1111 "
#6410000
0$
0)
0(
00
01
0/
07
08
06
1=
b1000 %
0>
0'
0.
05
0<
0,
0+
03
02
0:
09
1@
0?
0&
0-
04
1;
b0 "
b1000 !
#6460000
1)
b1001 %
1,
1'
b1 "
#6510000
0)
10
b1010 %
0,
13
0'
1.
b10 "
#6560000
1)
b1011 %
1,
1'
b11 "
#6610000
0)
00
17
b1100 %
0,
03
1:
0'
0.
15
b100 "
#6660000
1)
b1101 %
1,
1'
b101 "
#6710000
0)
10
b1110 %
0,
13
0'
1.
b110 "
#6760000
1)
b1111 %
1,
1'
b111 "
#6810000
0)
00
07
0=
b0 %
1$
0,
03
0:
0@
1?
0'
0.
05
1<
b1000 "
#6860000
1)
b1 %
1,
1'
b1001 "
#6910000
0)
10
b10 %
0,
13
0'
1.
b1010 "
#6960000
1)
b11 %
1,
1'
b1011 "
#7010000
0)
00
17
b100 %
0,
03
1:
0'
0.
15
b1100 "
#7060000
1)
b101 %
1,
1'
b1101 "
#7110000
0)
10
b110 %
0,
13
0'
1.
b1110 "
#7160000
1)
b111 %
1,
1'
b1111 "
#7210000
00
07
1=
0$
03
0:
1@
0?
1)
b1001 %
0(
0'
0.
05
0<
1,
0+
1&
b0 "
b1001 !
#7260000
10
0)
b1010 %
1(
0,
1+
1'
b1 "
#7310000
07
0/
1)
0(
10
b1011 %
01
1,
0+
13
0'
1.
b10 "
#7360000
17
1/
00
11
0)
b1100 %
1(
0,
1+
1'
b11 "
#7410000
0$
1=
0>
0/
06
1)
0(
00
01
17
b1101 %
08
1,
0+
03
1:
0'
0.
15
b100 "
#7460000
10
0)
b1110 %
1(
0,
1+
1'
b101 "
#7510000
0$
1=
0>
06
17
08
0/
1)
0(
10
b1111 %
01
1,
0+
13
0'
1.
b110 "
#7560000
1$
0=
1>
16
07
18
1/
00
11
0)
b0 %
1(
0,
1+
1'
b111 "
#7610000
0/
06
1)
0(
00
01
07
08
0=
b1 %
0>
1,
0+
03
0:
0@
1?
0'
0.
05
1<
b1000 "
#7660000
10
0)
b10 %
1(
0,
1+
1'
b1001 "
#7710000
07
0/
1)
0(
10
b11 %
01
1,
0+
13
0'
1.
b1010 "
#7760000
17
1/
00
11
0)
b100 %
1(
0,
1+
1'
b1011 "
#7810000
0=
0/
06
1)
0(
00
01
17
b101 %
08
1,
0+
03
1:
0'
0.
15
b1100 "
#7860000
10
0)
b110 %
1(
0,
1+
1'
b1101 "
#7910000
0=
06
17
08
0/
1)
0(
10
b111 %
01
1,
0+
13
0'
1.
b1110 "
#7960000
1=
16
07
18
1/
00
11
0)
b1000 %
1(
0,
1+
1'
b1111 "
#8010000
06
08
1=
0>
0$
0/
0:
1@
0?
0)
0(
10
b1010 %
01
0'
0.
05
0<
0,
0+
13
02
0&
1-
b0 "
b1010 !
#8060000
1)
b1011 %
1,
1'
b1 "
#8110000
17
0)
00
b1100 %
1/
0,
03
12
0'
1.
b10 "
#8160000
1)
b1101 %
1,
1'
b11 "
#8210000
0$
1=
0>
06
0)
10
0/
17
b1110 %
08
0,
13
02
1:
0'
0.
15
b100 "
#8260000
1)
b1111 %
1,
1'
b101 "
#8310000
1$
0=
1>
16
07
18
0)
00
b0 %
1/
0,
03
12
0'
1.
b110 "
#8360000
1)
b1 %
1,
1'
b111 "
#8410000
06
0)
10
0/
07
08
0=
b10 %
0>
0,
13
02
0:
0@
1?
0'
0.
05
1<
b1000 "
#8460000
1)
b11 %
1,
1'
b1001 "
#8510000
17
0)
00
b100 %
1/
0,
03
12
0'
1.
b1010 "
#8560000
1)
b101 %
1,
1'
b1011 "
#8610000
0=
06
0)
10
0/
17
b110 %
08
0,
13
02
1:
0'
0.
15
b1100 "
#8660000
1)
b111 %
1,
1'
b1101 "
#8710000
1=
16
07
18
0)
00
b1000 %
1/
0,
03
12
0'
1.
b1110 "
#8760000
1)
b1001 %
1,
1'
b1111 "
#8810000
0/
10
06
07
08
1=
0>
0$
01
13
02
0:
1@
0?
1)
b1011 %
0(
0'
0.
05
0<
1,
0+
1&
b0 "
b1011 !
#8860000
17
1/
00
11
0)
b1100 %
1(
0,
1+
1'
b1 "
#8910000
1)
0(
00
b1101 %
01
1,
0+
03
12
0'
1.
b10 "
#8960000
10
0)
b1110 %
1(
0,
1+
1'
b11 "
#9010000
0$
1=
0>
06
1)
0(
10
01
0/
17
b1111 %
08
1,
0+
13
02
1:
0'
0.
15
b100 "
#9060000
1$
0=
1>
16
07
18
1/
00
11
0)
b0 %
1(
0,
1+
1'
b101 "
#9110000
1)
0(
00
b1 %
01
1,
0+
03
12
0'
1.
b110 "
#9160000
10
0)
b10 %
1(
0,
1+
1'
b111 "
#9210000
06
1)
0(
10
01
0/
07
08
0=
b11 %
0>
1,
0+
13
02
0:
0@
1?
0'
0.
05
1<
b1000 "
#9260000
17
1/
00
11
0)
b100 %
1(
0,
1+
1'
b1001 "
#9310000
1)
0(
00
b101 %
01
1,
0+
03
12
0'
1.
b1010 "
#9360000
10
0)
b110 %
1(
0,
1+
1'
b1011 "
#9410000
0=
06
1)
0(
10
01
0/
17
b111 %
08
1,
0+
13
02
1:
0'
0.
15
b1100 "
#9460000
1=
16
07
18
1/
00
11
0)
b1000 %
1(
0,
1+
1'
b1101 "
#9510000
1)
0(
00
b1001 %
01
1,
0+
03
12
0'
1.
b1110 "
#9560000
10
0)
b1010 %
1(
0,
1+
1'
b1111 "
#9610000
1=
0>
0$
06
1@
0?
0)
0(
00
01
0/
17
b1100 %
08
0'
0.
05
0<
0,
0+
03
02
1:
09
0&
0-
14
b0 "
b1100 !
#9660000
1)
b1101 %
1,
1'
b1 "
#9710000
0)
10
b1110 %
0,
13
0'
1.
b10 "
#9760000
1)
b1111 %
1,
1'
b11 "
#9810000
1$
0=
1>
0)
00
07
b0 %
16
0,
03
0:
19
0'
0.
15
b100 "
#9860000
1)
b1 %
1,
1'
b101 "
#9910000
0)
10
b10 %
0,
13
0'
1.
b110 "
#9960000
1)
b11 %
1,
1'
b111 "
#10010000
0)
00
17
06
0=
b100 %
0>
0,
03
1:
09
0@
1?
0'
0.
05
1<
b1000 "
#10060000
1)
b101 %
1,
1'
b1001 "
#10110000
0)
10
b110 %
0,
13
0'
1.
b1010 "
#10160000
1)
b111 %
1,
1'
b1011 "
#10210000
1=
0)
00
07
b1000 %
16
0,
03
0:
19
0'
0.
15
b1100 "
#10260000
1)
b1001 %
1,
1'
b1101 "
#10310000
0)
10
b1010 %
0,
13
0'
1.
b1110 "
#10360000
1)
b1011 %
1,
1'
b1111 "
#10410000
00
17
06
1=
0>
0$
03
1:
09
1@
0?
1)
b1101 %
0(
0'
0.
05
0<
1,
0+
1&
b0 "
b1101 !
#10460000
10
0)
b1110 %
1(
0,
1+
1'
b1 "
#10510000
0$
1=
0>
06
17
08
0/
1)
0(
10
b1111 %
01
1,
0+
13
0'
1.
b10 "
#10560000
1$
0=
1>
16
07
18
1/
00
11
0)
b0 %
1(
0,
1+
1'
b11 "
#10610000
0/
1)
0(
00
01
07
b1 %
08
1,
0+
03
0:
19
0'
0.
15
b100 "
#10660000
10
0)
b10 %
1(
0,
1+
1'
b101 "
#10710000
07
0/
1)
0(
10
b11 %
01
1,
0+
13
0'
1.
b110 "
#10760000
17
1/
00
11
0)
b100 %
1(
0,
1+
1'
b111 "
#10810000
0/
1)
0(
00
01
17
08
06
0=
b101 %
0>
1,
0+
03
1:
09
0@
1?
0'
0.
05
1<
b1000 "
#10860000
10
0)
b110 %
1(
0,
1+
1'
b1001 "
#10910000
0=
06
17
08
0/
1)
0(
10
b111 %
01
1,
0+
13
0'
1.
b1010 "
#10960000
1=
16
07
18
1/
00
11
0)
b1000 %
1(
0,
1+
1'
b1011 "
#11010000
0/
1)
0(
00
01
07
b1001 %
08
1,
0+
03
0:
19
0'
0.
15
b1100 "
#11060000
10
0)
b1010 %
1(
0,
1+
1'
b1101 "
#11110000
07
0/
1)
0(
10
b1011 %
01
1,
0+
13
0'
1.
b1110 "
#11160000
17
1/
00
11
0)
b1100 %
1(
0,
1+
1'
b1111 "
#11210000
06
1=
0>
0$
0/
1:
09
1@
0?
0)
0(
10
b1110 %
01
0'
0.
05
0<
0,
0+
13
02
0&
1-
b0 "
b1110 !
#11260000
1)
b1111 %
1,
1'
b1 "
#11310000
1$
0=
1>
16
07
18
0)
00
b0 %
1/
0,
03
12
0'
1.
b10 "
#11360000
1)
b1 %
1,
1'
b11 "
#11410000
0)
10
0/
07
b10 %
08
0,
13
02
0:
19
0'
0.
15
b100 "
#11460000
1)
b11 %
1,
1'
b101 "
#11510000
17
0)
00
b100 %
1/
0,
03
12
0'
1.
b110 "
#11560000
1)
b101 %
1,
1'
b111 "
#11610000
0)
10
0/
17
08
06
0=
b110 %
0>
0,
13
02
1:
09
0@
1?
0'
0.
05
1<
b1000 "
#11660000
1)
b111 %
1,
1'
b1001 "
#11710000
1=
16
07
18
0)
00
b1000 %
1/
0,
03
12
0'
1.
b1010 "
#11760000
1)
b1001 %
1,
1'
b1011 "
#11810000
0)
10
0/
07
b1010 %
08
0,
13
02
0:
19
0'
0.
15
b1100 "
#11860000
1)
b1011 %
1,
1'
b1101 "
#11910000
17
0)
00
b1100 %
1/
0,
03
12
0'
1.
b1110 "
#11960000
1)
b1101 %
1,
1'
b1111 "
#12010000
0/
10
17
08
06
1=
0>
0$
01
13
02
1:
09
1@
0?
1)
b1111 %
0(
0'
0.
05
0<
1,
0+
1&
b0 "
b1111 !
#12060000
1$
0=
1>
16
07
18
1/
00
11
0)
b0 %
1(
0,
1+
1'
b1 "
#12110000
1)
0(
00
b1 %
01
1,
0+
03
12
0'
1.
b10 "
#12160000
10
0)
b10 %
1(
0,
1+
1'
b11 "
#12210000
1)
0(
10
01
0/
07
b11 %
08
1,
0+
13
02
0:
19
0'
0.
15
b100 "
#12260000
17
1/
00
11
0)
b100 %
1(
0,
1+
1'
b101 "
#12310000
1)
0(
00
b101 %
01
1,
0+
03
12
0'
1.
b110 "
#12360000
10
0)
b110 %
1(
0,
1+
1'
b111 "
#12410000
1)
0(
10
01
0/
17
08
06
0=
b111 %
0>
1,
0+
13
02
1:
09
0@
1?
0'
0.
05
1<
b1000 "
#12460000
1=
16
07
18
1/
00
11
0)
b1000 %
1(
0,
1+
1'
b1001 "
#12510000
1)
0(
00
b1001 %
01
1,
0+
03
12
0'
1.
b1010 "
#12560000
10
0)
b1010 %
1(
0,
1+
1'
b1011 "
#12610000
1)
0(
10
01
0/
07
b1011 %
08
1,
0+
13
02
0:
19
0'
0.
15
b1100 "
#12660000
17
1/
00
11
0)
b1100 %
1(
0,
1+
1'
b1101 "
#12710000
1)
0(
00
b1101 %
01
1,
0+
03
12
0'
1.
b1110 "
#12760000
10
0)
b1110 %
1(
0,
1+
1'
b1111 "
#12810000
0=
1>
07
18
00
11
1*
1,
13
1:
1@
1(
1/
16
1$
0+
02
09
0?
0&
0-
04
0;
1'
1.
15
1<
0)
b0 %
b0 "
b0 !
1#
#12860000
0$
1=
0>
06
17
08
0/
10
01
0(
1)
b1111 %
0*
0,
0'
b1 "
#12910000
1(
0)
1*
10
b1110 %
1,
03
1'
0.
b10 "
#12960000
00
0(
1)
b1101 %
0*
0,
0'
b11 "
#13010000
1/
11
1(
0)
1*
00
17
b1100 %
1,
13
0:
1'
1.
05
b100 "
#13060000
07
0/
10
01
0(
1)
b1011 %
0*
0,
0'
b101 "
#13110000
1(
0)
1*
10
b1010 %
1,
03
1'
0.
b110 "
#13160000
00
0(
1)
b1001 %
0*
0,
0'
b111 "
#13210000
16
18
1/
11
1(
0)
1*
00
07
1=
b1000 %
1,
13
1:
0@
1'
1.
15
0<
b1000 "
#13260000
0=
06
17
08
0/
10
01
0(
1)
b111 %
0*
0,
0'
b1001 "
#13310000
1(
0)
1*
10
b110 %
1,
03
1'
0.
b1010 "
#13360000
00
0(
1)
b101 %
0*
0,
0'
b1011 "
#13410000
1/
11
1(
0)
1*
00
17
b100 %
1,
13
0:
1'
1.
05
b1100 "
#13460000
07
0/
10
01
0(
1)
b11 %
0*
0,
0'
b1101 "
#13510000
1(
0)
1*
10
b10 %
1,
03
1'
0.
b1110 "
#13560000
00
0(
1)
b1 %
0*
0,
0'
b1111 "
#13610000
1$
1>
16
18
1/
11
07
0=
1(
1+
13
1:
1@
1)
b1 %
0*
1'
1.
15
1<
0,
1&
b0 "
b1 !
#13660000
1$
0=
1>
16
07
18
1/
00
11
0)
b0 %
1*
1(
1,
0+
0'
b1 "
#13710000
0$
1=
0>
06
17
08
0/
1)
0*
10
b1111 %
01
0,
1+
03
1'
0.
b10 "
#13760000
10
0)
b1110 %
1*
1(
1,
0+
0'
b11 "
#13810000
1/
1)
0*
00
11
17
b1101 %
0,
1+
13
0:
1'
1.
05
b100 "
#13860000
17
1/
00
11
0)
b1100 %
1*
1(
1,
0+
0'
b101 "
#13910000
07
0/
1)
0*
10
b1011 %
01
0,
1+
03
1'
0.
b110 "
#13960000
10
0)
b1010 %
1*
1(
1,
0+
0'
b111 "
#14010000
16
18
1/
1)
0*
00
11
07
1=
b1001 %
0,
1+
13
1:
0@
1'
1.
15
0<
b1000 "
#14060000
1=
16
07
18
1/
00
11
0)
b1000 %
1*
1(
1,
0+
0'
b1001 "
#14110000
0=
06
17
08
0/
1)
0*
10
b111 %
01
0,
1+
03
1'
0.
b1010 "
#14160000
10
0)
b110 %
1*
1(
1,
0+
0'
b1011 "
#14210000
1/
1)
0*
00
11
17
b101 %
0,
1+
13
0:
1'
1.
05
b1100 "
#14260000
17
1/
00
11
0)
b100 %
1*
1(
1,
0+
0'
b1101 "
#14310000
07
0/
1)
0*
10
b11 %
01
0,
1+
03
1'
0.
b1110 "
